pysciidoc/__init__.py
pysciidoc/_functools.py
pysciidoc/_module_discovery.py
pysciidoc/generate.py
pysciidoc/main.py
pysciidoc/objectdoc.py
pysciidoc/py.typed
pysciidoc/python_type_formatters.py
pysciidoc-0.3.3.dist-info/METADATA
pysciidoc-0.3.3.dist-info/WHEEL
pysciidoc-0.3.3.dist-info/entry_points.txt
pysciidoc-0.3.3.dist-info/RECORD
