Metadata-Version: 2.4
Name: pysciidoc
Version: 0.3.3
Summary: autogenerate asciidoc api documenation from docstrings
Requires-Python: >=3.10
Requires-Dist: click>=8.1.7
